gcrypto/__init__.py
gcrypto/gcrypto.py
gcrypto-0.1.0.dist-info/licenses/LICENSE
gcrypto-0.1.0.dist-info/METADATA
gcrypto-0.1.0.dist-info/WHEEL
gcrypto-0.1.0.dist-info/top_level.txt
gcrypto-0.1.0.dist-info/RECORD
