Metadata-Version: 2.4
Name: gcrypto
Version: 0.1.0
Summary: A small symetric crypto package
Author-email: Gil Weisbord <gil.weisbord@gmail.com>
License: MIT
Project-URL: Homepage, https://github.com/pypa/gcrypto
Project-URL: Issues, https://github.com/pypa/gcrypto/issues
Classifier: Programming Language :: Python :: 3
Classifier: License :: OSI Approved :: MIT License
Classifier: Operating System :: OS Independent
Requires-Python: >=3.8
License-File: LICENSE
Requires-Dist: pycryptodome
Dynamic: license-file
